calculatorSC.py
calculatorSC-0.0.1.dist-info/METADATA
calculatorSC-0.0.1.dist-info/WHEEL
calculatorSC-0.0.1.dist-info/top_level.txt
calculatorSC-0.0.1.dist-info/RECORD
