Metadata-Version: 2.1
Name: calculatorSC
Version: 0.0.1
Summary: Calculator simulation
Author: Stefan Chivu
License: UNKNOWN
Platform: UNKNOWN
Classifier: Programming Language :: Python :: 3
Classifier: License :: OSI Approved :: MIT License
Classifier: Operating System :: OS Independent
Requires-Python: >=3.6
